doctestfn/__init__.py
doctestfn/doctestfn.py
doctestfn-1.0.3.dist-info/METADATA
doctestfn-1.0.3.dist-info/WHEEL
doctestfn-1.0.3.dist-info/entry_points.txt
doctestfn-1.0.3.dist-info/top_level.txt
doctestfn-1.0.3.dist-info/RECORD
