Metadata-Version: 2.1
Name: doctestfn
Version: 1.0.3
Summary: Run doctests for a single function
Home-page: https://github.com/jncraton/doctestfn
Author: Jon Craton
Author-email: jon@joncraton.com
License: UNKNOWN
Platform: UNKNOWN
Classifier: Programming Language :: Python :: 3
Classifier: License :: OSI Approved :: MIT License
Classifier: Operating System :: OS Independent
Requires-Python: >=3.6
